scrapebadger/__init__.py
scrapebadger/client.py
scrapebadger/py.typed
scrapebadger/_internal/__init__.py
scrapebadger/_internal/client.py
scrapebadger/_internal/config.py
scrapebadger/_internal/exceptions.py
scrapebadger/_internal/pagination.py
scrapebadger/twitter/__init__.py
scrapebadger/twitter/client.py
scrapebadger/twitter/communities.py
scrapebadger/twitter/geo.py
scrapebadger/twitter/lists.py
scrapebadger/twitter/models.py
scrapebadger/twitter/trends.py
scrapebadger/twitter/tweets.py
scrapebadger/twitter/users.py
scrapebadger-0.1.8.dist-info/METADATA
scrapebadger-0.1.8.dist-info/WHEEL
scrapebadger-0.1.8.dist-info/licenses/LICENSE
scrapebadger-0.1.8.dist-info/RECORD
