Metadata-Version: 2.4
Name: scrapebadger
Version: 0.1.8
Summary: Official Python SDK for ScrapeBadger - Async web scraping APIs for Twitter and more
Project-URL: Homepage, https://scrapebadger.com
Project-URL: Documentation, https://docs.scrapebadger.com
Project-URL: Repository, https://github.com/scrapebadger/scrapebadger-python
Project-URL: Issues, https://github.com/scrapebadger/scrapebadger-python/issues
Project-URL: Changelog, https://github.com/scrapebadger/scrapebadger-python/blob/main/CHANGELOG.md
Author-email: ScrapeBadger <support@scrapebadger.com>
Maintainer-email: ScrapeBadger <support@scrapebadger.com>
License: MIT
License-File: LICENSE
Keywords: api,async,data-extraction,scraping,sdk,social-media,twitter,web-scraping
Classifier: Development Status :: 4 - Beta
Classifier: Framework :: AsyncIO
Classifier: Intended Audience :: Developers
Classifier: License :: OSI Approved :: MIT License
Classifier: Operating System :: OS Independent
Classifier: Programming Language :: Python :: 3
Classifier: Programming Language :: Python :: 3.10
Classifier: Programming Language :: Python :: 3.11
Classifier: Programming Language :: Python :: 3.12
Classifier: Programming Language :: Python :: 3.13
Classifier: Topic :: Internet :: WWW/HTTP
Classifier: Topic :: Software Development :: Libraries :: Python Modules
Classifier: Typing :: Typed
Requires-Python: >=3.10
Requires-Dist: httpx>=0.27.0
Requires-Dist: pydantic>=2.0.0
Provides-Extra: dev
Requires-Dist: mypy>=1.13.0; extra == 'dev'
Requires-Dist: pre-commit>=4.0.0; extra == 'dev'
Requires-Dist: pytest-asyncio>=0.24.0; extra == 'dev'
Requires-Dist: pytest-cov>=5.0.0; extra == 'dev'
Requires-Dist: pytest>=8.0.0; extra == 'dev'
Requires-Dist: respx>=0.21.0; extra == 'dev'
Requires-Dist: ruff>=0.8.0; extra == 'dev'
